clovers/__init__.py
clovers/config.py
clovers/core.py
clovers/logger.py
clovers/protocol.py
clovers/utils.py
clovers-0.4.8.dist-info/LICENSE
clovers-0.4.8.dist-info/METADATA
clovers-0.4.8.dist-info/WHEEL
clovers-0.4.8.dist-info/RECORD
